README.md
setup.py
tdlc_sqlalchemy/__init__.py
tdlc_sqlalchemy/base.py
tdlc_sqlalchemy/dialect.py
tdlc_sqlalchemy/types.py
tdlc_sqlalchemy/version.py
tencentcloud_dlc_sqlalchemy.egg-info/PKG-INFO
tencentcloud_dlc_sqlalchemy.egg-info/SOURCES.txt
tencentcloud_dlc_sqlalchemy.egg-info/dependency_links.txt
tencentcloud_dlc_sqlalchemy.egg-info/entry_points.txt
tencentcloud_dlc_sqlalchemy.egg-info/requires.txt
tencentcloud_dlc_sqlalchemy.egg-info/top_level.txt