Metadata-Version: 2.4
Name: tencentcloud-dlc-sqlalchemy
Version: 1.3.1
Summary: Tencentcloud DLC SQLAlchemy, using DLC dialect .
Author: Tencentcloud DLC Team.
Maintainer-email: valuxzhao@tencent.com
License: Apache License Version 2.0
Keywords: TencentCloud,DLC,sqlalchemy
Platform: any
Requires-Dist: tencentcloud-dlc-connector
Dynamic: author
Dynamic: keywords
Dynamic: license
Dynamic: maintainer-email
Dynamic: platform
Dynamic: requires-dist
Dynamic: summary
